dirku/__init__.py
dirku/collisionDetection/__init__.py
dirku/collisionDetection/collisionDetection.py
dirku/collisionDetection/selfcollisionDetection.py
dirku/geometricTransformations/__init__.py
dirku/geometricTransformations/geometricTransformations.py
dirku/interpolation/__init__.py
dirku/interpolation/cubic.py
dirku/interpolation/linear.py
dirku/interpolation/nearest.py
dirku/numericalIntegration/__init__.py
dirku/numericalIntegration/numericalIntegration.py
dirku/optimization/ADMM.py
dirku/optimization/__init__.py
dirku/optimization/gradientDescent.py
dirku/optimization/optim_gradientDescentBacktracking.py
dirku/postprocessing/__init__.py
dirku/postprocessing/measure_dice.py
dirku/postprocessing/measure_intersection.py
dirku/postprocessing/measure_inverseConsistency.py
dirku/postprocessing/measure_jacobian.py
dirku/postprocessing/measure_landmarks.py
dirku/postprocessing/measure_selfintersection.py
dirku/postprocessing/measure_shear.py
dirku/postprocessing/postprocessing_utils.py
dirku/postprocessing/visual_convergence.py
dirku/postprocessing/visual_grid.py
dirku/postprocessing/visual_pullback.py
dirku/postprocessing/visual_shear.py
dirku/postprocessing/visual_vector.py
dirku/regularization/__init__.py
dirku/regularization/regularization_l2.py
dirku/regularization/regularization_linearOperator.py
dirku/regularization/regularization_svk.py
dirku/similarityMeasure/__init__.py
dirku/similarityMeasure/similarityMeasure.py
dirku/utils/__init__.py
dirku/utils/points.py
dirku/utils/sdf.py
dirku-1.0.1.dist-info/METADATA
dirku-1.0.1.dist-info/WHEEL
dirku-1.0.1.dist-info/top_level.txt
dirku-1.0.1.dist-info/RECORD
